LICENSE
MANIFEST.in
README.md
README.md2rst
requirements.txt
setup.py
parallelforeachsubmodule/__init__.py
parallelforeachsubmodule/__main__.py
parallelforeachsubmodule/chunker.py
parallelforeachsubmodule/main.py
parallelforeachsubmodule/metadata.py
parallelforeachsubmodule/pfs.py
parallelforeachsubmodule/process.py
parallelforeachsubmodule/scheduler.py
parallelforeachsubmodule/status.py
pfs.egg-info/PKG-INFO
pfs.egg-info/SOURCES.txt
pfs.egg-info/dependency_links.txt
pfs.egg-info/entry_points.txt
pfs.egg-info/top_level.txt