Metadata-Version: 2.1
Name: pfs
Version: 0.5.16
Summary: Tool for "git submodule foreach" execution in parallel 
Home-page: https://github.com/RDCH106/parallel_foreach_submodule
Author: Rubén de Celis Hernández
Author-email: contact@rdch106.hol.es
License: LGPL v3
Download-URL: https://github.com/RDCH106/parallel_foreach_submodule/archive/v0.5.16.tar.gz
Keywords: git parallel submodule windows gnu-linux
Platform: UNKNOWN
Classifier: Programming Language :: Python
Classifier: Programming Language :: Python :: 2.7
Classifier: Programming Language :: Python :: 3.3
Classifier: Programming Language :: Python :: 3.4
Classifier: Programming Language :: Python :: 3.5
Classifier: Programming Language :: Python :: 3.6
Classifier: Programming Language :: Python :: 3.7
